pyqt_chat_widget/__init__.py
pyqt_chat_widget/chatWidget.py
pyqt_chat_widget-0.0.13.dist-info/LICENSE
pyqt_chat_widget-0.0.13.dist-info/METADATA
pyqt_chat_widget-0.0.13.dist-info/WHEEL
pyqt_chat_widget-0.0.13.dist-info/top_level.txt
pyqt_chat_widget-0.0.13.dist-info/RECORD
